safemath/__init__.py
safemath/cli.py
safemath/config.py
safemath/core.py
safemath/numpy_utils.py
safemath/pandas_utils.py
safemath/safenumber.py
safemath-1.1.0.dist-info/licenses/LICENSE
safemath-1.1.0.dist-info/METADATA
safemath-1.1.0.dist-info/WHEEL
safemath-1.1.0.dist-info/entry_points.txt
safemath-1.1.0.dist-info/top_level.txt
safemath-1.1.0.dist-info/RECORD
