Metadata-Version: 2.4
Name: safemath
Version: 1.1.0
Summary: Bulletproof mathematical operations for Python with intelligent fallback handling
Author-email: Aman Choudhary <aman.1727.2706@gmail.com>
License: MIT
Project-URL: Homepage, https://github.com/amanchoudhary1727/safemath
Project-URL: Repository, https://github.com/amanchoudhary1727/safemath
Project-URL: Documentation, https://github.com/amanchoudhary1727/safemath#readme
Keywords: mathematics,safe,numpy,pandas,division-by-zero,data-science,reliability,fallback,robust,crash-free,mathematical-operations,error-handling,numerical-computing
Classifier: Development Status :: 5 - Production/Stable
Classifier: Intended Audience :: Developers
Classifier: Intended Audience :: Science/Research
Classifier: License :: OSI Approved :: MIT License
Classifier: Operating System :: OS Independent
Classifier: Programming Language :: Python :: 3
Classifier: Programming Language :: Python :: 3.8
Classifier: Programming Language :: Python :: 3.9
Classifier: Programming Language :: Python :: 3.10
Classifier: Programming Language :: Python :: 3.11
Classifier: Programming Language :: Python :: 3.12
Classifier: Topic :: Scientific/Engineering :: Mathematics
Requires-Python: >=3.8
License-File: LICENSE
Requires-Dist: numpy>=1.19.0
Requires-Dist: pandas>=1.3.0
Dynamic: license-file
